wres/__init__.py
wres-1.0.3.dist-info/DESCRIPTION.rst
wres-1.0.3.dist-info/METADATA
wres-1.0.3.dist-info/RECORD
wres-1.0.3.dist-info/WHEEL
wres-1.0.3.dist-info/entry_points.txt
wres-1.0.3.dist-info/metadata.json
wres-1.0.3.dist-info/top_level.txt
